{
    "metadata": {
        "start_settings": {
            "bg_color": [60, 98, 232],
            "ground_color": [62, 77, 153],
            "position": [-10, 0],
            "gamemode": "cube",
            "speed": "normal",
            "gravity": "normal",
            "default_color_channels": {
                "1": [0, 0, 0],
                "2": [255, 255, 255],
                "3": [255, 0, 0],
                "4": [0, 255, 0]
            }
        },
        "type": "created",
        "name": "my first leve",
        "description": "Test level for new level editor",
        "song_filepath": "./assets/audio/StereoMadness.ogg",
        "created_timestamp": 0,
        "modified_timestamp": 0,
        "song_start_time": 0,
        "total_attempts": 0,
        "progress_normal": 0,
        "progress_practice": 0 
    },
    "leveldata": [
        [
            null,
            null,
            {
                "type": "yellow_orb",
                "rotation": "up",
                "reflection": "none",
                "color1_channel": null,
                "color2_channel": null
            },
            null,
            null,
            null,
            {
                "type": "spike",
                "rotation": "left",
                "reflection": "none",
                "color1_channel": 3,
                "color2_channel": 2
            },
            {
                "type": "spike",
                "rotation": "right",
                "reflection": "none",
                "color1_channel": 4,
                "color2_channel": 3
            }
        ],
        [
            {
                "type": "block0_1",
                "rotation": "right",
                "reflection": "none",
                "color1_channel": 1,
                "color2_channel": 2
            },
            null,
            {
                "type": "spike",
                "rotation": "up",
                "reflection": "none",
                "color1_channel": 1,
                "color2_channel": 2
            },
            null,
            null,
            null,
            {
                "type": "spike",
                "rotation": "left",
                "reflection": "none",
                "color1_channel": 3,
                "color2_channel": 2
            },
            {
                "type": "spike",
                "rotation": "right",
                "reflection": "none",
                "color1_channel": 4,
                "color2_channel": 3
            }
        ],
        [
            {
                "type": "block0_0",
                "rotation": "up",
                "reflection": "none",
                "color1_channel": 1,
                "color2_channel": 2
            },
            {
                "type": "block0_3",
                "rotation": "up",
                "reflection": "none",
                "color1_channel": 1,
                "color2_channel": 2
            },
            {
                "type": "block0_1",
                "rotation": "up",
                "reflection": "horizontal",
                "color1_channel": 1,
                "color2_channel": 2
            },
            null,
            null,
            null,
            {
                "type": "spike",
                "rotation": "left",
                "reflection": "none",
                "color1_channel": 3,
                "color2_channel": 2
            },
            {
                "type": "spike",
                "rotation": "right",
                "reflection": "none",
                "color1_channel": 4,
                "color2_channel": 3
            }
        ]
    ]
}